Jpeg2gif/__init__.py
Jpeg2gif/core.py
Jpeg2gif/jpgToGif.py
Jpeg2gif/utils.py
Jpeg2gif/version.py
jpeg2gif-0.0.5.dist-info/licenses/LICENSE
jpeg2gif-0.0.5.dist-info/METADATA
jpeg2gif-0.0.5.dist-info/WHEEL
jpeg2gif-0.0.5.dist-info/top_level.txt
jpeg2gif-0.0.5.dist-info/RECORD
